<OpenSearchDescription xmlns="http://a9.com/-/spec/opensearch/1.1/"
                       xmlns:moz="http://www.mozilla.org/2006/browser/search/">
  <ShortName>Nix Darwin - Options Search</ShortName>
  <Description>Find nix darwin options quickly.</Description>
  <InputEncoding>UTF-8</InputEncoding>
  <Image width="16" height="16" type="image/x-icon">https://ndo.xinux.uz/images/favicon.png</Image>
  <Url type="text/html" template="https://ndo.xinux.uz/?query={searchTerms}"/>
  <moz:SearchForm>https://ndo.xinux.uz/</moz:SearchForm>
</OpenSearchDescription>
